torch_knn.cpython-39-x86_64-linux-gnu.so
torch_kdtree/__init__.py
torch_kdtree/nn_distance.py
torch_kdtree/torch_knn.cpython-39-x86_64-linux-gnu.so
torch_kdtree-1.0.dist-info/LICENSE
torch_kdtree-1.0.dist-info/METADATA
torch_kdtree-1.0.dist-info/WHEEL
torch_kdtree-1.0.dist-info/top_level.txt
torch_kdtree-1.0.dist-info/RECORD
